Workbook
Name ______LSS01: #REF!
Name ______LSS01: #REF!
Name ______LSS01: #REF!
Name _____LSS01: #REF!
Name _____LSS01: #REF!
Name ____LSS01: #REF!
Name ____LSS01: #REF!
Name ____LSS01: #REF!
Name ___01: '[1]#REF'!#REF!
Name ___02: '[1]#REF'!#REF!
Name ___03: '[1]#REF'!#REF!
Name ___04: '[1]#REF'!#REF!
Name ___05: '[1]#REF'!#REF!
Name ___06: '[1]#REF'!#REF!
Name ___LSS01: #REF!
Name ___LSS01: #REF!
Name ___LSS01: #REF!
Name __01: '[1]#REF'!#REF!
Name __02: '[1]#REF'!#REF!
Name __03: '[1]#REF'!#REF!
Name __04: '[1]#REF'!#REF!
Name __05: '[1]#REF'!#REF!
Name __06: '[1]#REF'!#REF!
Name __A123: #REF!
Name __A123: #REF!
Name __A123: #REF!
Name __A334: #REF!
Name __A334: #REF!
Name __A334: #REF!
Name __LSS01: #REF!
Name __LSS01: #REF!
Name __LSS01: #REF!
Name _01: '[1]#REF'!#REF!
Name _02: '[1]#REF'!#REF!
Name _03: '[1]#REF'!#REF!
Name _04: '[1]#REF'!#REF!
Name _05: '[1]#REF'!#REF!
Name _06: '[1]#REF'!#REF!
Name _4_01: '[1]#REF'!#REF!
Name _4_01: '[1]#REF'!#REF!
Name _4_01: '[1]#REF'!#REF!
Name _5_02: '[1]#REF'!#REF!
Name _5_02: '[1]#REF'!#REF!
Name _5_02: '[1]#REF'!#REF!
Name _6_03: '[1]#REF'!#REF!
Name _6_03: '[1]#REF'!#REF!
Name _6_03: '[1]#REF'!#REF!
Name _7_04: '[1]#REF'!#REF!
Name _7_04: '[1]#REF'!#REF!
Name _7_04: '[1]#REF'!#REF!
Name _8_05: '[1]#REF'!#REF!
Name _8_05: '[1]#REF'!#REF!
Name _8_05: '[1]#REF'!#REF!
Name _9_06: '[1]#REF'!#REF!
Name _9_06: '[1]#REF'!#REF!
Name _9_06: '[1]#REF'!#REF!
Name _A123: #REF!
Name _A123: #REF!
Name _A123: #REF!
Name _A334: #REF!

Sheet CI & PL
A1: COMMERCIAL INVOICE AND PACKING LIST
A2: ① SHIPPER / EXPORTER | K2: ⑧ NO. & DATE OF INVOICE
A3: AMOTECH CO., LTD. | L3: VMC-ANT-190820A | O3: 43697
A4: 1 LOT. 5BLOCK NAMDONG-GONGDAN | K4: ⑨ PAYMENT TERMS
A5: 617 NAMCHON DONG, NAMDONG-GU
A6: INCHEON CITY, KOREA | K6: ⑩ DELIVERY TERMS
L7: CIF | M7: =E22 -> HANOI, VIETNAM
A8: ② SHIP TO ADDRESS 운송주소 | K8: ⑪ REMARKS
A9: AMO VINA CO., LTD.
A10: LOT CN 13, KHAI QUANG INDUSTRIAL ZONE, | K10: 신고 07AC 해투 00089
A11: KHAI QUANG WARD, VINH YEN CITY | K11: 37
A12: VINH PHUC PROVINCE, VIETNAM
A13: TAX CODE : 2500517382
A14: ATTN : Ms. Van (Thanh Van) / vinatrade@amotech.co.kr / MP : (+84) 969-00-99-60 | K14: " FREIGHT PREPAID "
A15: ③ BUYER / BILL TO ADDRESS 수출면허상 구매자
A16: SAME AS ABOVE
A21: ④ PORT OF LOADING | E21: ⑤ FINAL DESTINATION
A22: INCHEON, KOREA | E22: HANOI, VIETNAM
A23: ⑥ CARRIER | E23: ⑦ SAILING ON OR ABOUT
A24: BY AIR | E24: =O3 -> 43697
A26: SHIP. MARKS | C26: HS CODE | D26: M/C NAME | E26: MODEL NO. | F26: SERIAL NO. | G26: NEW/USED | H26: PRODUCTION YEAR | I26: MANUFACTURER | J26: C/O/O | K26: Q'TY | L26: U/P | M26: AMOUNT | N26: PALLET NO. | O26: NET W. | P26: GROSS W.
A27: AMO VINA | C27: ='MC List for Amovina'!F7 -> 8422.40-9030 | D27: ='MC List for Amovina'!G7 -> VACUUM PACKING M/C | E27: ='MC List for Amovina'!H7 -> GVD-45E | F27: ='MC List for Amovina'!I7 -> E19081403 | G27: ='MC List for Amovina'!J7 -> NEW | H27: ='MC List for Amovina'!K7 -> 2019 | I27: ='MC List for Amovina'!L7 -> GASUNG PACK | J27: ='MC List for Amovina'!M7 -> KOREA | K27: ='MC List for Amovina'!N7 -> 1 | L27: 3256 | M27: =K27*L27 -> 3256 | N27: 1-1 | O27: ='Packing Details'!G6 -> 11 | P27: ='Packing Details'!H6 -> 11
A28: VIETNAM
A29: =N26 -> PALLET NO. | B29: =N42 -> 1-1
A30: =L3 -> VMC-ANT-190820A
A31: =D26 -> M/C NAME
A32: =J26 -> C/O/O
C42: TOTAL | K42: =SUM(K27:K41) -> 1 | M42: =SUM(M27:M41) -> 3256 | N42: =N27 -> 1-1 | O42: =SUM(O27:O41) -> 11 | P42: =SUM(P27:P41) -> 11
A49: 운임 : | B49: 520000
A50: 보험료 : | B50: =M42*110%*0.0189%*1150 -> 778.46076 | L50: SIGNED BY

Sheet Packing Details
B2: Packing Details
B4: NO. | C4: ITEM NAME (ENG) 품명 (영문) | D4: MODEL NO. 모델넘버 | E4: SERIAL NO. 시리얼 넘버 | F4: PALLET NO. | G4: NET WEIGHT | H4: GROSS WEIGHT | I4: DIM.(mm) | J4: PACKING PICTURE 포장사진 (포장 전 현물 / 포장진행 / 포장완료 사진)
B5: 1 | C5: Cisco Webex DX80 | D5: CP-DX80-K9 | E5: FOC2327KLW3 | F5: 1 | G5: 11 | H5: 11 | I5: 700*240*740
B6: TOTAL | F6: =F5 -> 1 | G6: =SUM(G5:G5) -> 11 | H6: =SUM(H5:H5) -> 11

Sheet MC List for Amovina
B2: conferencing equipment for Amovina | E2: 사업부 | F2: NFC ANT | G2: 출하 가능일자 | H2: 43696 | I2: 항공/해상 | J2: 항공
E3: 프로젝트 | G3: 도착 필요일자 | H3: 43697 | I3: 항공일 경우 사유 | J3: 긴급 양산이관
B4: ▶▶▶ 영문작성 필수
B5: NO. | C5: ITEM PICTURE 설비 사진 | D5: NAME PLATE PICTURE 명판 사진 | E5: ITEM NAME (KOR) 품명 (국문) | F5: HS CODE | G5: ITEM NAME (ENG) 품명 (영문) | H5: MODEL NO. 모델넘버 | I5: SERIAL NO. 시리얼 넘버 | J5: NEW/USED 신품/중고 | K5: PRODUCTION YEAR 생산연도 | L5: MANUFACTURER 제조사 | M5: COUNTRY OF ORIGIN 원산지 | N5: QUANTITY 수량 | O5: PURPOSE 목적 | P5: SERVICE VOLTAGE 사용전압 | Q5: POWER 전력 (1SET) | R5: SPECIFICATION 규격(1SET) | V5: P.I.C. 담당자 | W5: USAGE 용도 ★반드시 영문+국문작성 | X5: OPERATING PRINCIPLE 작동원리 ★반드시 영문+국문작성 | Y5: HOW TO USE 작동방법 ★반드시 영문+국문작성 | Z5: REMARK 비고
R6: WIDTH (MM) | S6: LENGTH (MM) | T6: HEIGHT (MM) | U6: WEIGHT (KG)
B7: 1 | E7: 화상회의장비 | F7: 8422.40-9030 | G7: VACUUM PACKING M/C | H7: GVD-45E | I7: E19081403 | J7: NEW | K7: 2019 | L7: GASUNG PACK | M7: KOREA | N7: 1 | O7: PACKING | P7: 220 | Q7: 60 | R7: 520 | S7: 490 | T7: 1060 | U7: 80 | V7: 이석인 | W7: PACKING | X7: 전원 맟 에어 설치 후 가동 | Y7: 1. main power, air Installation 2. start

Sheet Investment Contract
B2: INVESTMENT CONTRACT OF MACHINE & EQUIPMENT
I4: Contract No. : | J4: ='CI & PL'!L3 -> VMC-ANT-190820A
I5: Date : | J5: ='CI & PL'!O3 -> 43697
A7: 1. The Investor : AMOTECH CO., LTD.
B8: - Representative : Kim Pyung kyu, Jeong Jun hwan
B9: - Address : 1 LOT. 5BLOCK NAMDONG-GONGDAN, 617 NAMCHON DONG, NAMDONG-GU, INCHEON CITY, KOREA
B10: (Hereinafter refer to as the "Investor")
A12: 2. The Investee : AMO VINA CO., LTD.
B13: - Representative : Jeong Kyu hyuk
B14: - Address : LOT CN 13, KHAI QUANG INDUSTRIAL ZONE, KHAI QUANG WARD, VINH YEN CITY, VINH PHUC PROVINCE, VIETNAM
B15: (Hereinafter refer to as the "Investee")
B17: It has been mutually agreed by both parties to sign this contract under the following terms and conditions:
A19: ARTICLE 1. Investment in Kind
B20: 1.1 Investment amount : | C20: ='CI & PL'!M42 -> 3256
B21: 1.2 Machine & Equipment list
B22: ITEM NAME | C22: MODEL NO. | D22: SERIAL NO. | E22: NEW/USED | F22: PRODUCTION YEAR | G22: MANUFACTURER | H22: COO | I22: Q'TY | J22: U/P | K22: AMOUNT
B23: ='CI & PL'!D27 -> VACUUM PACKING M/C | C23: ='CI & PL'!E27 -> GVD-45E | D23: ='CI & PL'!F27 -> E19081403 | E23: ='CI & PL'!G27 -> NEW | F23: ='CI & PL'!H27 -> 2019 | G23: ='CI & PL'!I27 -> GASUNG PACK | H23: ='CI & PL'!J27 -> KOREA | I23: ='CI & PL'!K27 -> 1 | J23: ='CI & PL'!L27 -> 3256 | K23: =I23*J23 -> 3256
B24: TOTAL | I24: =SUM(I23:I23) -> 1 | K24: =SUM(K23:K23) -> 3256 | L24: =IF(K24=C20,TRUE) -> TRUE
A26: ARTICLE 2. Country of origin of Machine & Equipment
B27: 2.1 Country of origin : As above list
A28: ARTICLE 3. Packing of Machine & Equipment
B29: 3.1 Export standard packing
A30: ARTICLE 4. Payment
B31: 4.1 The above investment in kind of Machine & Equipment is applied to NO COMMERCIAL VALUE.
A32: ARTICLE 5. Documentation
B33: 5.1 The Investor shall send to the Investee all necessary documents such as; detailed drawing, instructions, manuals relating to the machine & equipment.
B34: 5.2 The Investor shall send a full set of draft documents to the Investee before delivery date for the local import procedure.
A35: ARTICLE 6. General Conditions
B36: 6.1 Both parties guarantee to fulfill terms and conditions of this contract completely and strictly.
B37: 6.2 Both parties will discuss problems to solve them and any revision must be confirmed by written form.
B38: 6.3 This contract is made in 02 in English copies with the same value.
B39: 6.4 Validity : From the signing date
A41: The Investor : AMOTECH CO., LTD. | G41: The Investee : AMO VINA CO., LTD.
